LICENSE
MANIFEST.in
README.md
VERSION
requirements-test.txt
requirements.txt
setup.cfg
setup.py
gtxamqp/__init__.py
gtxamqp/connector.py
gtxamqp/consumer.py
gtxamqp/delegate.py
gtxamqp/facade.py
gtxamqp/factory.py
gtxamqp/pool.py
gtxamqp/protocol.py
gtxamqp/utils.py
gtxamqp.egg-info/PKG-INFO
gtxamqp.egg-info/SOURCES.txt
gtxamqp.egg-info/dependency_links.txt
gtxamqp.egg-info/requires.txt
gtxamqp.egg-info/top_level.txt
gtxamqp/spec/amqp0-8.rabbitmq.xml
gtxamqp/spec/amqp0-9-1.rabbitmq.xml
tests/__init__.py
tests/test_basic_publish.py
tests/test_channel_closed.py
tests/test_client.py
tests/test_pool.py
tests/test_teardown.py
tests/test_topic_exchange.py
tests/utils.py