Metadata-Version: 1.1
Name: gtxamqp
Version: 2.1.13
Summary: AMQP Reconnecting Client for Twisted
Home-page: http://github.com/devsenexx/gtxamqp
Author: Oded Lazar
Author-email: odedlaz@gmail.com
License: MIT License
Platform: linux
Classifier: Programming Language :: Python
Classifier: Development Status :: 4 - Beta
Classifier: Natural Language :: English
Classifier: Intended Audience :: Developers
Classifier: Operating System :: OS Independent
Classifier: Topic :: Software Development :: Libraries :: Python Modules
Classifier: Topic :: Software Development :: Libraries :: Application Frameworks
